{
  "meta": {
    "runId": "HarmoneyOpenEye_20260401-132719",
    "generatedAt": "2026-04-01T05:42:29.955Z",
    "pageId": "AppLifecycle",
    "counts": {
      "features": 6,
      "flows": 8
    }
  },
  "page": {
    "pageId": "AppLifecycle",
    "entry": {
      "filePath": "",
      "structName": "AppLifecycle",
      "line": 0,
      "description": "应用生命周期"
    }
  },
  "features": [
    {
      "featureId": "src_AppLifecycle_onCreate_11_8c0837a5",
      "title": "应用创建时",
      "kind": "source",
      "anchor": {
        "filePath": "input/app/HarmoneyOpenEye/entry/src/main/ets/entryability/EntryAbility.ts",
        "line": 11,
        "functionName": "onCreate"
      },
      "counts": {
        "flows": 1,
        "nodes": 2,
        "edges": 1
      }
    },
    {
      "featureId": "src_AppLifecycle_onDestroy_15_499479af",
      "title": "应用退出时",
      "kind": "source",
      "anchor": {
        "filePath": "input/app/HarmoneyOpenEye/entry/src/main/ets/entryability/EntryAbility.ts",
        "line": 15,
        "functionName": "onDestroy"
      },
      "counts": {
        "flows": 1,
        "nodes": 2,
        "edges": 1
      }
    },
    {
      "featureId": "src_AppLifecycle_onWindowStageCreate_19_f65897e0",
      "title": "主窗口创建时",
      "kind": "source",
      "anchor": {
        "filePath": "input/app/HarmoneyOpenEye/entry/src/main/ets/entryability/EntryAbility.ts",
        "line": 19,
        "functionName": "onWindowStageCreate"
      },
      "counts": {
        "flows": 3,
        "nodes": 9,
        "edges": 6
      }
    },
    {
      "featureId": "src_AppLifecycle_onWindowStageDestroy_67_1607f730",
      "title": "主窗口销毁时",
      "kind": "source",
      "anchor": {
        "filePath": "input/app/HarmoneyOpenEye/entry/src/main/ets/entryability/EntryAbility.ts",
        "line": 67,
        "functionName": "onWindowStageDestroy"
      },
      "counts": {
        "flows": 1,
        "nodes": 3,
        "edges": 2
      }
    },
    {
      "featureId": "src_AppLifecycle_onForeground_72_8b194a00",
      "title": "应用切到前台时",
      "kind": "source",
      "anchor": {
        "filePath": "input/app/HarmoneyOpenEye/entry/src/main/ets/entryability/EntryAbility.ts",
        "line": 72,
        "functionName": "onForeground"
      },
      "counts": {
        "flows": 1,
        "nodes": 3,
        "edges": 2
      }
    },
    {
      "featureId": "src_AppLifecycle_onBackground_77_7d899c7f",
      "title": "应用切到后台时",
      "kind": "source",
      "anchor": {
        "filePath": "input/app/HarmoneyOpenEye/entry/src/main/ets/entryability/EntryAbility.ts",
        "line": 77,
        "functionName": "onBackground"
      },
      "counts": {
        "flows": 1,
        "nodes": 3,
        "edges": 2
      }
    }
  ]
}
